ey_commerce_lib/__init__.py
ey_commerce_lib/model.py
ey_commerce_lib/py.typed
ey_commerce_lib/dxm/__init__.py
ey_commerce_lib/dxm/main.py
ey_commerce_lib/dxm/constant/__init__.py
ey_commerce_lib/dxm/constant/order.py
ey_commerce_lib/dxm/exception/__init__.py
ey_commerce_lib/dxm/exception/common.py
ey_commerce_lib/dxm/parser/__init__.py
ey_commerce_lib/dxm/parser/common.py
ey_commerce_lib/dxm/parser/count.py
ey_commerce_lib/dxm/parser/ebay_product.py
ey_commerce_lib/dxm/parser/export_template.py
ey_commerce_lib/dxm/parser/order.py
ey_commerce_lib/dxm/parser/purchase.py
ey_commerce_lib/dxm/parser/tracking.py
ey_commerce_lib/dxm/parser/warehouse.py
ey_commerce_lib/dxm/schemas/__init__.py
ey_commerce_lib/dxm/schemas/common.py
ey_commerce_lib/dxm/schemas/dxm_commodity_product.py
ey_commerce_lib/dxm/schemas/ebay_product.py
ey_commerce_lib/dxm/schemas/export_package.py
ey_commerce_lib/dxm/schemas/order.py
ey_commerce_lib/dxm/schemas/tracking.py
ey_commerce_lib/dxm/schemas/warehouse.py
ey_commerce_lib/dxm/utils/__init__.py
ey_commerce_lib/dxm/utils/dxm_commodity_product.py
ey_commerce_lib/dxm/utils/mark.py
ey_commerce_lib/four_seller/__init__.py
ey_commerce_lib/four_seller/main.py
ey_commerce_lib/four_seller/constant/__init__.py
ey_commerce_lib/four_seller/constant/response.py
ey_commerce_lib/four_seller/parser/__init__.py
ey_commerce_lib/four_seller/parser/order.py
ey_commerce_lib/four_seller/schemas/__init__.py
ey_commerce_lib/four_seller/schemas/query/__init__.py
ey_commerce_lib/four_seller/schemas/query/order.py
ey_commerce_lib/four_seller/schemas/vo/__init__.py
ey_commerce_lib/four_seller/schemas/vo/order.py
ey_commerce_lib/kogan/__init__.py
ey_commerce_lib/kogan/main.py
ey_commerce_lib/kogan/schemas/__init__.py
ey_commerce_lib/kogan/schemas/query/__init__.py
ey_commerce_lib/kogan/schemas/query/order.py
ey_commerce_lib/kogan/schemas/query/product.py
ey_commerce_lib/kogan/schemas/response/__init__.py
ey_commerce_lib/kogan/schemas/response/order.py
ey_commerce_lib-1.0.30.dist-info/METADATA
ey_commerce_lib-1.0.30.dist-info/WHEEL
ey_commerce_lib-1.0.30.dist-info/RECORD
