Metadata-Version: 2.4
Name: ey-commerce-lib
Version: 1.0.30
Summary: eeyoung电商客户端调用封装
Author-email: 饶奇奇 <1124393197@qq.com>
Requires-Python: >=3.10
Requires-Dist: ddddocr>=1.5.6
Requires-Dist: httpx>=0.28.1
Requires-Dist: lxml>=5.3.2
Requires-Dist: playwright>=1.52.0
Requires-Dist: pydantic>=2.11.3
Requires-Dist: pytest-asyncio>=0.26.0
Requires-Dist: pytest>=8.3.5
